{"connect":{"statusCode":200,"response":{"id":"","name":"OKEX","private":false,"enableRateLimit":true,"countries":["CN","US"],"rateLimit":1000,"has":{"loadMarkets":"true","cancelAllOrders":"false","cancelOrder":"true","cancelOrders":"false","CORS":"false","createDepositAddress":"false","createLimitOrder":"true","createMarketOrder":"true","createOrder":"true","deposit":"false","editOrder":"emulated","fetchBalance":"true","fetchBidsAsks":"false","fetchClosedOrders":"true","fetchCurrencies":"false","fetchDepositAddress":"true","fetchDeposits":"true","fetchFundingFees":"false","fetchL2OrderBook":"true","fetchLedger":"true","fetchMarkets":"true","fetchMyTrades":"true","fetchOHLCV":"true","fetchOpenOrders":"true","fetchOrder":"true","fetchOrderBook":"true","fetchOrderBooks":"false","fetchOrders":"false","fetchOrderTrades":"true","fetchStatus":"emulated","fetchTicker":"true","fetchTickers":"true","fetchTime":"true","fetchTrades":"true","fetchTradingFee":"false","fetchTradingFees":"false","fetchTradingLimits":"false","fetchTransactions":"false","fetchWithdrawals":"true","privateAPI":"true","publicAPI":"true","withdraw":"true","futures":"true"},"urls":{"logo":"https://user-images.githubusercontent.com/1294454/32552768-0d6dd3c6-c4a6-11e7-90f8-c043b64756a7.jpg","api":{"rest":"https://www.{hostname}"},"www":"https://www.okex.com","doc":"https://www.okex.com/docs/en/","fees":"https://www.okex.com/pages/products/fees.html","referral":"https://www.okex.com/join/1888677","test":{"rest":"https://testnet.okex.com"}}}},"markets":{"statusCode":408},"ticker":{"statusCode":504,"response":""},"tickers":{"statusCode":504,"response":""},"orderBook":{"statusCode":504,"response":""},"trades":{"statusCode":504,"response":""}}